PoProofRead-0.2.0.data/data/share/applications/poproofread.desktop
PoProofRead-0.2.0.data/data/share/mime/packages/poproofread.xml
PoProofRead-0.2.0.data/data/share/poproofread/64.png
PoProofRead-0.2.0.data/scripts/poproofread-gtk
poproofread/__init__.py
poproofread/core.py
poproofread/custom_exceptions.py
poproofread/dialogs_gtk.py
poproofread/fileio.py
poproofread/i18n.py
poproofread/poproofread_gtk.py
poproofread/settings.py
poproofread/graphics/14.png
poproofread/graphics/192.png
poproofread/graphics/622.png
poproofread/graphics/64.png
poproofread/graphics/code_overview.odg
poproofread/graphics/code_overview.png
poproofread/graphics/icon_original.odg
poproofread/graphics/icon_original.png
poproofread/gui/about_dialog.glade
poproofread/gui/encoding_selection_dialog.glade
poproofread/gui/file_chooser_dialog_open.glade
poproofread/gui/file_chooser_dialog_save_as.glade
poproofread/gui/jump_to_dialog.glade
poproofread/gui/message_dialog_ok.glade
poproofread/gui/poproofread_gtk_gui.glade
poproofread/gui/question_dialog.glade
PoProofRead-0.2.0.dist-info/COPYING
PoProofRead-0.2.0.dist-info/METADATA
PoProofRead-0.2.0.dist-info/WHEEL
PoProofRead-0.2.0.dist-info/top_level.txt
PoProofRead-0.2.0.dist-info/RECORD
